pyopenms/Constants.py
pyopenms/__init__.py
pyopenms/__init__.pyi
pyopenms/_all_modules.py
pyopenms/_all_modules.pyi
pyopenms/_dataframes.py
pyopenms/_pyopenms_1.cpython-311-x86_64-linux-gnu.so
pyopenms/_pyopenms_1.pyi
pyopenms/_pyopenms_2.cpython-311-x86_64-linux-gnu.so
pyopenms/_pyopenms_2.pyi
pyopenms/_pyopenms_3.cpython-311-x86_64-linux-gnu.so
pyopenms/_pyopenms_3.pyi
pyopenms/_pyopenms_4.cpython-311-x86_64-linux-gnu.so
pyopenms/_pyopenms_4.pyi
pyopenms/_pyopenms_5.cpython-311-x86_64-linux-gnu.so
pyopenms/_pyopenms_5.pyi
pyopenms/_pyopenms_6.cpython-311-x86_64-linux-gnu.so
pyopenms/_pyopenms_6.pyi
pyopenms/_pyopenms_7.cpython-311-x86_64-linux-gnu.so
pyopenms/_pyopenms_7.pyi
pyopenms/_pyopenms_8.cpython-311-x86_64-linux-gnu.so
pyopenms/_pyopenms_8.pyi
pyopenms/_python_extras.py
pyopenms/_qt_version_info.py
pyopenms/_sysinfo.py
pyopenms/_version.py
pyopenms/plotting.py
pyopenms/py.typed
pyopenms/version.py
pyopenms/share/OpenMS/CHEMISTRY/Custom_RNA_modifications.tsv
pyopenms/share/OpenMS/CHEMISTRY/Enzymes.xml
pyopenms/share/OpenMS/CHEMISTRY/Enzymes_RNA.xml
pyopenms/share/OpenMS/CHEMISTRY/HMDBMappingFile.tsv
pyopenms/share/OpenMS/CHEMISTRY/MetaboliteIsoModel.scale
pyopenms/share/OpenMS/CHEMISTRY/MetaboliteIsoModel.svm
pyopenms/share/OpenMS/CHEMISTRY/MetaboliteIsoModelNoised2.scale
pyopenms/share/OpenMS/CHEMISTRY/MetaboliteIsoModelNoised2.svm
pyopenms/share/OpenMS/CHEMISTRY/MetaboliteIsoModelNoised5.scale
pyopenms/share/OpenMS/CHEMISTRY/MetaboliteIsoModelNoised5.svm
pyopenms/share/OpenMS/CHEMISTRY/Modomics.json
pyopenms/share/OpenMS/CHEMISTRY/Modomics.tsv
pyopenms/share/OpenMS/CHEMISTRY/NegativeAdducts.tsv
pyopenms/share/OpenMS/CHEMISTRY/OMSSA_modification_mapping
pyopenms/share/OpenMS/CHEMISTRY/PSI-MOD.obo
pyopenms/share/OpenMS/CHEMISTRY/PositiveAdducts.tsv
pyopenms/share/OpenMS/CHEMISTRY/XLMOD.obo
pyopenms/share/OpenMS/CHEMISTRY/XTandem_default_config.xml
pyopenms/share/OpenMS/CHEMISTRY/XTandem_residue_mass.bioml.xml
pyopenms-3.5.0.dist-info/METADATA
pyopenms-3.5.0.dist-info/WHEEL
pyopenms-3.5.0.dist-info/top_level.txt
pyopenms-3.5.0.dist-info/RECORD
pyopenms-3.5.0.dist-info/sboms/auditwheel.cdx.json
